geekros/__init__.py
geekros/module/__init__.py
geekros/module/mic_array/__init__.py
geekros/package/__init__.py
geekros/package/voice/__init__.py
geekros/package/voice/detection.py
geekros/package/voice/recorder.py
geekros/package/voice/wakeup.py
geekros/utils/__init__.py
geekros/utils/loging/__init__.py
geekros-1.0.2.dist-info/METADATA
geekros-1.0.2.dist-info/WHEEL
geekros-1.0.2.dist-info/top_level.txt
geekros-1.0.2.dist-info/RECORD
