Metadata-Version: 2.1
Name: geekros
Version: 1.0.2
Summary: Python development framework for geekros.
Home-page: https://github.com/geekros/geekros
Author: MakerYang
Author-email: admin@wileho.com
License: Apache-2.0
Project-URL: Documentation, https://www.geekros.com/docs
Project-URL: Website, https://geekros.com
Project-URL: Source, https://github.com/geekros/geekros
Keywords: webrtc,realtime,audio,video,geekros,ros,ros2,ubuntu,openai,llm,llama
Platform: UNKNOWN
Classifier: Intended Audience :: Developers
Classifier: License :: OSI Approved :: Apache Software License
Classifier: Topic :: Multimedia :: Sound/Audio
Classifier: Topic :: Multimedia :: Video
Classifier: Topic :: Scientific/Engineering :: Artificial Intelligence
Classifier: Programming Language :: Python :: 3
Classifier: Programming Language :: Python :: 3.9
Classifier: Programming Language :: Python :: 3.10
Classifier: Programming Language :: Python :: 3 :: Only
Requires-Python: >=3.9.0
Requires-Dist: colorlog>=6.8.2
Requires-Dist: logging>=0.4.9.6
Requires-Dist: numpy>=1.26.4
Requires-Dist: openai>=1.42.0
Requires-Dist: pyaudio>=0.2.14
Requires-Dist: pyserial>=3.2.1
Requires-Dist: requests>=2.32.3
Requires-Dist: websocket-client==0.48.0
